setup.py
django_sherlock.egg-info/PKG-INFO
django_sherlock.egg-info/SOURCES.txt
django_sherlock.egg-info/dependency_links.txt
django_sherlock.egg-info/requires.txt
django_sherlock.egg-info/top_level.txt
sherlock/__init__.py
sherlock/admin.py
sherlock/base.py
sherlock/managers.py
sherlock/models.py
sherlock/observers.py
sherlock/publishers.py
sherlock/storage.py
tests/polls/__init__.py
tests/polls/admin.py
tests/polls/models.py
tests/polls/observers.py
tests/polls/publishers.py
tests/polls/signals.py
tests/polls/tests/__init__.py
tests/polls/tests/managers.py
tests/polls/tests/method_logger.py
tests/polls/tests/observers.py