Metadata-Version: 1.0
Name: django-sherlock
Version: 0.1.0
Summary: A pluggable app for notifications
Home-page: https://github.com/geeknam/django-sherlock
Author: Nam Ngo
Author-email: nam@namis.me
License: UNKNOWN
Platform: UNKNOWN
Classifier: Framework :: Django
Classifier: Intended Audience :: Developers
Classifier: License :: OSI Approved :: BSD License
Classifier: Operating System :: OS Independent
Classifier: Topic :: Software Development
